abd_clam/__init__.py
abd_clam/anomaly_detection/__init__.py
abd_clam/anomaly_detection/anomaly_dataset.py
abd_clam/anomaly_detection/anomaly_space.py
abd_clam/anomaly_detection/chaoda.py
abd_clam/anomaly_detection/graph_scorers.py
abd_clam/anomaly_detection/meta_ml.py
abd_clam/anomaly_detection/pretrained_models.py
abd_clam/anomaly_detection/training.py
abd_clam/classification/__init__.py
abd_clam/classification/classifier.py
abd_clam/core/__init__.py
abd_clam/core/cluster.py
abd_clam/core/cluster_criteria.py
abd_clam/core/dataset.py
abd_clam/core/graph.py
abd_clam/core/graph_criteria.py
abd_clam/core/metric.py
abd_clam/core/space.py
abd_clam/search/__init__.py
abd_clam/search/cakes.py
abd_clam/utils/__init__.py
abd_clam/utils/constants.py
abd_clam/utils/helpers.py
abd_clam/utils/synthetic_data.py
abd_clam-0.22.3.dist-info/LICENSE
abd_clam-0.22.3.dist-info/METADATA
abd_clam-0.22.3.dist-info/WHEEL
abd_clam-0.22.3.dist-info/RECORD
